myrocketsimulator/MRSguidance.py
myrocketsimulator/MRSlib.py
myrocketsimulator/MRSrocket.py
myrocketsimulator/MRSvislib.py
myrocketsimulator/data/.DS_Store
myrocketsimulator/data/Blue_Marble_2002-2.png
myrocketsimulator/data/MoonSurface.jpg
myrocketsimulator/data/defaultMRSmission.py
myrocketsimulator/data/egm96_to360.ascii.txt
myrocketsimulator-1.2.0.dist-info/LICENSE.txt
myrocketsimulator-1.2.0.dist-info/METADATA
myrocketsimulator-1.2.0.dist-info/WHEEL
myrocketsimulator-1.2.0.dist-info/top_level.txt
myrocketsimulator-1.2.0.dist-info/RECORD
