Metadata-Version: 2.1
Name: myrocketsimulator
Version: 1.2.0
Summary: MyRocketSimulator is a Python package designed to simulate spacecrafts launching from Earth and orbiting around it or flying to the Moon.
Author-email: Thibault Bautze-Scherff <admin@myrocketsimulator.com>
License: MIT License
Project-URL: repository, https://github.com/ThibaultBS/MyRocketSimulator/tree/main
Project-URL: changelog, https://github.com/ThibaultBS/MyRocketSimulator/blob/main/changelog.md
Classifier: Programming Language :: Python :: 3
Classifier: License :: OSI Approved :: MIT License
Classifier: Operating System :: OS Independent
Requires-Python: >=3.7
License-File: LICENSE.txt
Requires-Dist: matplotlib >=3.5.0
Requires-Dist: skyfield >=1.45
Requires-Dist: pandas >=1.3.4
Requires-Dist: scipy >=1.7.1
Requires-Dist: spaceweather >=0.2.2
Requires-Dist: nrlmsise00 >=0.0.1
Requires-Dist: pyshtools >=4.10
Requires-Dist: numpy >=1.21.6
Requires-Dist: simplekml >=1.3.6
Requires-Dist: prettytable
